[
  {
    "id": "6290262",
    "name": "RIM, DIA. 18X12 W/ 4.85 HOLE & STUD",
    "imageUrl": "https://www.lego.com/cdn/product-assets/element.img.lod5photo.192x192/6290262.jpg",
    "rawText": "RIM, DIA. 18X12 W/ 4.85 HOLE & STUD\n\n6290262\n\nSelect this piece"
  },
  {
    "id": "6289747",
    "name": "LEFT PLATE 1X2, W/ BOW, 45 DEG. CUT",
    "imageUrl": "https://www.lego.com/cdn/product-assets/element.img.lod5photo.192x192/6289747.jpg",
    "rawText": "LEFT PLATE 1X2, W/ BOW, 45 DEG. CUT\n\n6289747\n\nSelect this piece"
  },
  {
    "id": "6437723",
    "name": "CHEST LID, 2X4, NO. 2",
    "imageUrl": "https://www.lego.com/cdn/product-assets/element.img.lod5photo.192x192/6437723.jpg",
    "rawText": "CHEST LID, 2X4, NO. 2\n\n6437723\n\nSelect this piece"
  },
  {
    "id": "6087084",
    "name": "CHERRY",
    "imageUrl": "https://www.lego.com/cdn/product-assets/element.img.lod5photo.192x192/6087084.jpg",
    "rawText": "CHERRY\n\n6087084\n\nSelect this piece"
  },
  {
    "id": "6312452",
    "name": "PLATE 1X1X2/3, OUTSIDE BOW",
    "imageUrl": "https://www.lego.com/cdn/product-assets/element.img.lod5photo.192x192/6312452.jpg",
    "rawText": "PLATE 1X1X2/3, OUTSIDE BOW\n\n6312452\n\nSelect this piece"
  },
  {
    "id": "6428803",
    "name": "SHAFT 3M Ø3.2",
    "imageUrl": "https://www.lego.com/cdn/product-assets/element.img.lod5photo.192x192/6428803.jpg",
    "rawText": "SHAFT 3M Ø3.2\n\n6428803\n\nSelect this piece"
  },
  {
    "id": "6670628",
    "name": "FOOT, PLATE",
    "imageUrl": "https://www.lego.com/cdn/product-assets/element.img.lod5photo.192x192/6670628.jpg",
    "rawText": "FOOT, PLATE\n\n6670628\n\nSelect this piece"
  },
  {
    "id": "6133933",
    "name": "PLATE ROUND W. 1 KNOB",
    "imageUrl": "https://www.lego.com/cdn/product-assets/element.img.lod5photo.192x192/6133933.jpg",
    "rawText": "PLATE ROUND W. 1 KNOB\n\n6133933\n\nSelect this piece"
  },
  {
    "id": "6421680",
    "name": "MUDGUARD 2X4X2, NO. 1",
    "imageUrl": "https://www.lego.com/cdn/product-assets/element.img.lod5photo.192x192/6421680.jpg",
    "rawText": "MUDGUARD 2X4X2, NO. 1\n\n6421680\n\nSelect this piece"
  },
  {
    "id": "6102596",
    "name": "TYRE LOW Ø24X12",
    "imageUrl": "https://www.lego.com/cdn/product-assets/element.img.lod5photo.192x192/6102596.jpg",
    "rawText": "TYRE LOW Ø24X12\n\n6102596\n\nSelect this piece"
  },
  {
    "id": "6423146",
    "name": "SHORTS, W/ HIP, NO. 15",
    "imageUrl": "https://www.lego.com/cdn/product-assets/element.img.lod5photo.192x192/6423146.jpg",
    "rawText": "SHORTS, W/ HIP, NO. 15\n\n6423146\n\nSelect this piece"
  },
  {
    "id": "362301",
    "name": "PLATE 1X3",
    "imageUrl": "https://www.lego.com/cdn/cs/set/assets/blt1eca764a9f683996/362301.jpg",
    "rawText": "PLATE 1X3\n\n362301\n\nSelect this piece"
  },
  {
    "id": "4550324",
    "name": "FLAT TILE 1X4",
    "imageUrl": "https://www.lego.com/cdn/cs/set/assets/blt980c2e2a75d670f2/4550324.jpg",
    "rawText": "FLAT TILE 1X4\n\n4550324\n\nSelect this piece"
  },
  {
    "id": "306221",
    "name": "ROUND BRICK 1X1",
    "imageUrl": "https://www.lego.com/cdn/cs/set/assets/bltc170ec215ac55b0d/306221.jpg",
    "rawText": "ROUND BRICK 1X1\n\n306221\n\nSelect this piece"
  },
  {
    "id": "6028736",
    "name": "PLATE 1X2",
    "imageUrl": "https://www.lego.com/cdn/cs/set/assets/bltaeefb322391927b0/6028736.jpg",
    "rawText": "PLATE 1X2\n\n6028736\n\nSelect this piece"
  },
  {
    "id": "371001",
    "name": "PLATE 1X4",
    "imageUrl": "https://www.lego.com/cdn/cs/set/assets/blta55739529b8e1803/371001.jpg",
    "rawText": "PLATE 1X4\n\n371001\n\nSelect this piece"
  },
  {
    "id": "6072668",
    "name": "FLAT TILE 1X4",
    "imageUrl": "https://www.lego.com/cdn/product-assets/element.img.lod5photo.192x192/6072668.jpg",
    "rawText": "FLAT TILE 1X4\n\n6072668\n\nSelect this piece"
  },
  {
    "id": "6322820",
    "name": "FLAT TILE 1X1, ROUND",
    "imageUrl": "https://www.lego.com/cdn/product-assets/element.img.lod5photo.192x192/6322820.jpg",
    "rawText": "FLAT TILE 1X1, ROUND\n\n6322820\n\nSelect this piece"
  },
  {
    "id": "6245272",
    "name": "ROOF TILE 1X1X2/3",
    "imageUrl": "https://www.lego.com/cdn/cs/set/assets/bltb4d29a24214ae7e2/6245272.jpg",
    "rawText": "ROOF TILE 1X1X2/3\n\n6245272\n\nSelect this piece"
  },
  {
    "id": "302124",
    "name": "PLATE 2X3",
    "imageUrl": "https://www.lego.com/cdn/cs/set/assets/blt5012b92fdf932086/302124.jpg",
    "rawText": "PLATE 2X3\n\n302124\n\nSelect this piece"
  },
  {
    "id": "6322904",
    "name": "FLAT TILE 1X1, ROUND \"NO. 35\"",
    "imageUrl": "https://www.lego.com/cdn/product-assets/element.img.lod5photo.192x192/6322904.jpg",
    "rawText": "FLAT TILE 1X1, ROUND \"NO. 35\"\n\n6322904\n\nSelect this piece"
  },
  {
    "id": "6271127",
    "name": "ANGLE PLATE 1X2/1X4",
    "imageUrl": "https://www.lego.com/cdn/product-assets/element.img.lod5photo.192x192/6271127.jpg",
    "rawText": "ANGLE PLATE 1X2/1X4\n\n6271127\n\nSelect this piece"
  },
  {
    "id": "6023173",
    "name": "ROOF TILE 1X1X2/3, ABS",
    "imageUrl": "https://www.lego.com/cdn/product-assets/element.img.lod5photo.192x192/6023173.jpg",
    "rawText": "ROOF TILE 1X1X2/3, ABS\n\n6023173\n\nSelect this piece"
  },
  {
    "id": "300101",
    "name": "BRICK 2X4",
    "imageUrl": "https://www.lego.com/cdn/product-assets/element.img.lod5photo.192x192/300101.jpg",
    "rawText": "BRICK 2X4\n\n300101\n\nSelect this piece"
  },
  {
    "id": "6249091",
    "name": "PLATE 1X4, W/ 2 KNOBS, NO. 2",
    "imageUrl": "https://www.lego.com/cdn/cs/set/assets/blt4e79610aa741353f/6249091.jpg",
    "rawText": "PLATE 1X4, W/ 2 KNOBS, NO. 2\n\n6249091\n\nSelect this piece"
  },
  {
    "id": "302323",
    "name": "PLATE 1X2",
    "imageUrl": "https://www.lego.com/cdn/cs/set/assets/bltdcdef93baf1454d9/302323.jpg",
    "rawText": "PLATE 1X2\n\n302323\n\nSelect this piece"
  },
  {
    "id": "6212758",
    "name": "PLATE 1X2, ROUNDED, NO. 1",
    "imageUrl": "https://www.lego.com/cdn/product-assets/element.img.lod5photo.192x192/6212758.jpg",
    "rawText": "PLATE 1X2, ROUNDED, NO. 1\n\n6212758\n\nSelect this piece"
  },
  {
    "id": "6035734",
    "name": "BOX 3X4",
    "imageUrl": "https://www.lego.com/cdn/product-assets/element.img.lod5photo.192x192/6035734.jpg",
    "rawText": "BOX 3X4\n\n6035734\n\nSelect this piece"
  },
  {
    "id": "4187743",
    "name": "PLATE 1X4",
    "imageUrl": "https://www.lego.com/cdn/cs/set/assets/blt32a827d15d06f701/4187743.jpg",
    "rawText": "PLATE 1X4\n\n4187743\n\nSelect this piece"
  },
  {
    "id": "4211397",
    "name": "PLATE 2X2",
    "imageUrl": "https://www.lego.com/cdn/product-assets/element.img.lod5photo.192x192/4211397.jpg",
    "rawText": "PLATE 2X2\n\n4211397\n\nSelect this piece"
  },
  {
    "id": "6580123",
    "name": "BI 3101, 88+4 42659 V29",
    "imageUrl": "https://www.lego.com/cdn/product-assets/element.img.lod5photo.192x192/6580123.jpg",
    "rawText": "BI 3101, 88+4 42659 V29\n\n6580123\n\nSelect this piece"
  },
  {
    "id": "6286881",
    "name": "FLAT TILE 2X3",
    "imageUrl": "https://www.lego.com/cdn/product-assets/element.img.lod5photo.192x192/6286881.jpg",
    "rawText": "FLAT TILE 2X3\n\n6286881\n\nSelect this piece"
  },
  {
    "id": "6469079",
    "name": "BRICK 2X2X1 INV. BOW, W/ CUT OUT",
    "imageUrl": "https://www.lego.com/cdn/product-assets/element.img.lod5photo.192x192/6469079.jpg",
    "rawText": "BRICK 2X2X1 INV. BOW, W/ CUT OUT\n\n6469079\n\nSelect this piece"
  },
  {
    "id": "6318084",
    "name": "ANGLE PLATE 1X2/1X4",
    "imageUrl": "https://www.lego.com/cdn/product-assets/element.img.lod5photo.192x192/6318084.jpg",
    "rawText": "ANGLE PLATE 1X2/1X4\n\n6318084\n\nSelect this piece"
  },
  {
    "id": "6056291",
    "name": "PLATE 2X2 W 1 KNOB",
    "imageUrl": "https://www.lego.com/cdn/product-assets/element.img.lod5photo.192x192/6056291.jpg",
    "rawText": "PLATE 2X2 W 1 KNOB\n\n6056291\n\nSelect this piece"
  },
  {
    "id": "6541665",
    "name": "TORSO, GIRL, W/ ARM, NO. 630",
    "imageUrl": "https://www.lego.com/cdn/product-assets/element.img.lod5photo.192x192/6541665.jpg",
    "rawText": "TORSO, GIRL, W/ ARM, NO. 630\n\n6541665\n\nSelect this piece"
  },
  {
    "id": "6416663",
    "name": "MINI DOLL, HEAD, NO. 338",
    "imageUrl": "https://www.lego.com/cdn/product-assets/element.img.lod5photo.192x192/6416663.jpg",
    "rawText": "MINI DOLL, HEAD, NO. 338\n\n6416663\n\nSelect this piece"
  },
  {
    "id": "4542391",
    "name": "PLATE 1X2 W. STICK",
    "imageUrl": "https://www.lego.com/cdn/product-assets/element.img.lod5photo.192x192/4542391.jpg",
    "rawText": "PLATE 1X2 W. STICK\n\n4542391\n\nSelect this piece"
  },
  {
    "id": "6003004",
    "name": "BRICK 1X4",
    "imageUrl": "https://www.lego.com/cdn/cs/set/assets/blt1e82bd4a0303dd55/6003004.jpg",
    "rawText": "BRICK 1X4\n\n6003004\n\nSelect this piece"
  },
  {
    "id": "6146221",
    "name": "WALL ELEMENT 1X2X1",
    "imageUrl": "https://www.lego.com/cdn/product-assets/element.img.lod5photo.192x192/6146221.jpg",
    "rawText": "WALL ELEMENT 1X2X1\n\n6146221\n\nSelect this piece"
  },
  {
    "id": "4558168",
    "name": "FLAT TILE 1X3",
    "imageUrl": "https://www.lego.com/cdn/cs/set/assets/bltb27d58276786afeb/4558168.jpg",
    "rawText": "FLAT TILE 1X3\n\n4558168\n\nSelect this piece"
  },
  {
    "id": "6158058",
    "name": "ANGLE PLATE 1X2 / 2X4",
    "imageUrl": "https://www.lego.com/cdn/product-assets/element.img.lod5photo.192x192/6158058.jpg",
    "rawText": "ANGLE PLATE 1X2 / 2X4\n\n6158058\n\nSelect this piece"
  },
  {
    "id": "6409768",
    "name": "MINI WIG, NO. 367",
    "imageUrl": "https://www.lego.com/cdn/product-assets/element.img.lod5photo.192x192/6409768.jpg",
    "rawText": "MINI WIG, NO. 367\n\n6409768\n\nSelect this piece"
  },
  {
    "id": "6287854",
    "name": "FLAT TILE 1X1, ROUND \"NO. 18\"",
    "imageUrl": "https://www.lego.com/cdn/product-assets/element.img.lod5photo.192x192/6287854.jpg",
    "rawText": "FLAT TILE 1X1, ROUND \"NO. 18\"\n\n6287854\n\nSelect this piece"
  },
  {
    "id": "6514185",
    "name": "WALL ELEMENT 1X2X2",
    "imageUrl": "https://www.lego.com/cdn/cs/set/assets/https://www.lego.com/cdn/cs/elements/assets/blt07a8843a78cdb8ec/6514185.jpg",
    "rawText": "WALL ELEMENT 1X2X2\n\n6514185\n\nSelect this piece"
  },
  {
    "id": "6439041",
    "name": "STICK Ø 3.2 W/ HOLDER",
    "imageUrl": "https://www.lego.com/cdn/product-assets/element.img.lod5photo.192x192/6439041.jpg",
    "rawText": "STICK Ø 3.2 W/ HOLDER\n\n6439041\n\nSelect this piece"
  },
  {
    "id": "302001",
    "name": "PLATE 2X4",
    "imageUrl": "https://www.lego.com/cdn/cs/set/assets/blt56ba9d7c51226a9e/302001.jpg",
    "rawText": "PLATE 2X4\n\n302001\n\nSelect this piece"
  },
  {
    "id": "4541455",
    "name": "TYRE LOW NARROW Ø24x7MM",
    "imageUrl": "https://www.lego.com/cdn/product-assets/element.img.lod5photo.192x192/4541455.jpg",
    "rawText": "TYRE LOW NARROW Ø24x7MM\n\n4541455\n\nSelect this piece"
  },
  {
    "id": "4211053",
    "name": "FLAT TILE 1X4",
    "imageUrl": "https://www.lego.com/cdn/product-assets/element.img.lod5photo.192x192/4211053.jpg",
    "rawText": "FLAT TILE 1X4\n\n4211053\n\nSelect this piece"
  },
  {
    "id": "6472960",
    "name": "PLATE 1X2X4 W. BALL",
    "imageUrl": "https://www.lego.com/cdn/product-assets/element.img.lod5photo.192x192/6472960.jpg",
    "rawText": "PLATE 1X2X4 W. BALL\n\n6472960\n\nSelect this piece"
  },
  {
    "id": "4164021",
    "name": "FLAT TILE 1X4",
    "imageUrl": "https://www.lego.com/cdn/cs/set/assets/blt41887ba7e35328d4/4164021.jpg",
    "rawText": "FLAT TILE 1X4\n\n4164021\n\nSelect this piece"
  },
  {
    "id": "6212989",
    "name": "FLAT TILE 2X4",
    "imageUrl": "https://www.lego.com/cdn/product-assets/element.img.lod5photo.192x192/6212989.jpg",
    "rawText": "FLAT TILE 2X4\n\n6212989\n\nSelect this piece"
  },
  {
    "id": "6099730",
    "name": "PLATE W. BOW 2X2X2/3",
    "imageUrl": "https://www.lego.com/cdn/product-assets/element.img.lod5photo.192x192/6099730.jpg",
    "rawText": "PLATE W. BOW 2X2X2/3\n\n6099730\n\nSelect this piece"
  },
  {
    "id": "6416546",
    "name": "MINI DOLL HEAD, NO. 14",
    "imageUrl": "https://www.lego.com/cdn/product-assets/element.img.lod5photo.192x192/6416546.jpg",
    "rawText": "MINI DOLL HEAD, NO. 14\n\n6416546\n\nSelect this piece"
  },
  {
    "id": "4212454",
    "name": "ROUND BRICK 1X1",
    "imageUrl": "https://www.lego.com/cdn/cs/set/assets/bltc7573ecd1ce21e56/4212454.jpg",
    "rawText": "ROUND BRICK 1X1\n\n4212454\n\nSelect this piece"
  },
  {
    "id": "6481595",
    "name": "PANTS, W/ HIP, NO. 39",
    "imageUrl": "https://www.lego.com/cdn/product-assets/element.img.lod5photo.192x192/6481595.jpg",
    "rawText": "PANTS, W/ HIP, NO. 39\n\n6481595\n\nSelect this piece"
  },
  {
    "id": "6528290",
    "name": "TORSO, GIRL, W/ ARM, NO. 611",
    "imageUrl": "https://www.lego.com/cdn/product-assets/element.img.lod5photo.192x192/6528290.jpg",
    "rawText": "TORSO, GIRL, W/ ARM, NO. 611\n\n6528290\n\nSelect this piece"
  },
  {
    "id": "6397831",
    "name": "SKATER HELMET",
    "imageUrl": "https://www.lego.com/cdn/product-assets/element.img.lod5photo.192x192/6397831.jpg",
    "rawText": "SKATER HELMET\n\n6397831\n\nSelect this piece"
  },
  {
    "id": "302023",
    "name": "PLATE 2X4",
    "imageUrl": "https://www.lego.com/cdn/cs/set/assets/blt1bd4f795d7f24e33/302023.jpg",
    "rawText": "PLATE 2X4\n\n302023\n\nSelect this piece"
  },
  {
    "id": "242001",
    "name": "CORNER PLATE 1X2X2",
    "imageUrl": "https://www.lego.com/cdn/cs/set/assets/blte590124664d22432/242001.jpg",
    "rawText": "CORNER PLATE 1X2X2\n\n242001\n\nSelect this piece"
  },
  {
    "id": "6044729",
    "name": "RIM NARROW Ø18x7 W HOLE Ø4.8",
    "imageUrl": "https://www.lego.com/cdn/product-assets/element.img.lod5photo.192x192/6044729.jpg",
    "rawText": "RIM NARROW Ø18x7 W HOLE Ø4.8\n\n6044729\n\nSelect this piece"
  },
  {
    "id": "6397823",
    "name": "PLATE 4X4",
    "imageUrl": "https://www.lego.com/cdn/product-assets/element.img.lod5photo.192x192/6397823.jpg",
    "rawText": "PLATE 4X4\n\n6397823\n\nSelect this piece"
  },
  {
    "id": "4666579",
    "name": "CONNECTOR PEG/CROSS AXLE",
    "imageUrl": "https://www.lego.com/cdn/cs/set/assets/blt31dd0cbe448ff6e3/4666579.jpg",
    "rawText": "CONNECTOR PEG/CROSS AXLE\n\n4666579\n\nSelect this piece"
  },
  {
    "id": "4211445",
    "name": "PLATE 1X4",
    "imageUrl": "https://www.lego.com/cdn/cs/set/assets/blt4b2e226d814a3da1/4211445.jpg",
    "rawText": "PLATE 1X4\n\n4211445\n\nSelect this piece"
  },
  {
    "id": "6409763",
    "name": "MINI WIG, NO. 369",
    "imageUrl": "https://www.lego.com/cdn/product-assets/element.img.lod5photo.192x192/6409763.jpg",
    "rawText": "MINI WIG, NO. 369\n\n6409763\n\nSelect this piece"
  },
  {
    "id": "6416470",
    "name": "DOG, W/ HOLE, DIA. 1.5, NO. 39",
    "imageUrl": "https://www.lego.com/cdn/product-assets/element.img.lod5photo.192x192/6416470.jpg",
    "rawText": "DOG, W/ HOLE, DIA. 1.5, NO. 39\n\n6416470\n\nSelect this piece"
  },
  {
    "id": "4612603",
    "name": "WALL CORNER 1X1X1",
    "imageUrl": "https://www.lego.com/cdn/product-assets/element.img.lod5photo.192x192/4612603.jpg",
    "rawText": "WALL CORNER 1X1X1\n\n4612603\n\nSelect this piece"
  },
  {
    "id": "6273227",
    "name": "PLATE 2X2 W BALL SOCKET W/CROS",
    "imageUrl": "https://www.lego.com/cdn/product-assets/element.img.lod5photo.192x192/6273227.jpg",
    "rawText": "PLATE 2X2 W BALL SOCKET W/CROS\n\n6273227\n\nSelect this piece"
  },
  {
    "id": "6289745",
    "name": "RIGHT PLATE 1X2, W/ BOW, 45 DEG. CUT",
    "imageUrl": "https://www.lego.com/cdn/product-assets/element.img.lod5photo.192x192/6289745.jpg",
    "rawText": "RIGHT PLATE 1X2, W/ BOW, 45 DEG. CUT\n\n6289745\n\nSelect this piece"
  },
  {
    "id": "6507789",
    "name": "TILE 1X2, 1/2 CIRCLE",
    "imageUrl": "https://www.lego.com/cdn/product-assets/element.img.lod5photo.192x192/6507789.jpg",
    "rawText": "TILE 1X2, 1/2 CIRCLE\n\n6507789\n\nSelect this piece"
  },
  {
    "id": "6020147",
    "name": "FLAT TILE 2X2",
    "imageUrl": "https://www.lego.com/cdn/product-assets/element.img.lod5photo.192x192/6020147.jpg",
    "rawText": "FLAT TILE 2X2\n\n6020147\n\nSelect this piece"
  },
  {
    "id": "303501",
    "name": "PLATE 4X8",
    "imageUrl": "https://www.lego.com/cdn/cs/set/assets/bltfab1b8ab56575339/303501.jpg",
    "rawText": "PLATE 4X8\n\n303501\n\nSelect this piece"
  },
  {
    "id": "4164022",
    "name": "BRICK 1X2",
    "imageUrl": "https://www.lego.com/cdn/cs/set/assets/blt854ac5523b76376a/4164022.jpg",
    "rawText": "BRICK 1X2\n\n4164022\n\nSelect this piece"
  },
  {
    "id": "6020073",
    "name": "PLATE 1X4",
    "imageUrl": "https://www.lego.com/cdn/cs/set/assets/bltd3fd55619339d911/6020073.jpg",
    "rawText": "PLATE 1X4\n\n6020073\n\nSelect this piece"
  },
  {
    "id": "6258135",
    "name": "PLATE 1X1X2/3, OUTSIDE BOW",
    "imageUrl": "https://www.lego.com/cdn/cs/set/assets/bltd005f948670791ef/6258135.jpg",
    "rawText": "PLATE 1X1X2/3, OUTSIDE BOW\n\n6258135\n\nSelect this piece"
  },
  {
    "id": "4211568",
    "name": "PLATE 1X2 WITH SLIDE",
    "imageUrl": "https://www.lego.com/cdn/cs/set/assets/bltccbd80bca79f1948/4211568.jpg",
    "rawText": "PLATE 1X2 WITH SLIDE\n\n4211568\n\nSelect this piece"
  },
  {
    "id": "241226",
    "name": "RADIATOR GRILLE 1X2",
    "imageUrl": "https://www.lego.com/cdn/cs/set/assets/blt5d25bf36e28392b2/241226.jpg",
    "rawText": "RADIATOR GRILLE 1X2\n\n241226\n\nSelect this piece"
  },
  {
    "id": "6510175",
    "name": "WINDSCREEN 2X6X2",
    "imageUrl": "https://www.lego.com/cdn/product-assets/element.img.lod5photo.192x192/6510175.jpg",
    "rawText": "WINDSCREEN 2X6X2\n\n6510175\n\nSelect this piece"
  },
  {
    "id": "6476484",
    "name": "CAMERA",
    "imageUrl": "https://www.lego.com/cdn/product-assets/element.img.lod5photo.192x192/6476484.jpg",
    "rawText": "CAMERA\n\n6476484\n\nSelect this piece"
  },
  {
    "id": "6136310",
    "name": "LIFE JACKET",
    "imageUrl": "https://www.lego.com/cdn/product-assets/element.img.lod5photo.192x192/6136310.jpg",
    "rawText": "LIFE JACKET\n\n6136310\n\nSelect this piece"
  },
  {
    "id": "6622623",
    "name": "ROOF TILE 2X2/45 INV.",
    "imageUrl": "https://www.lego.com/cdn/product-assets/element.img.lod5photo.192x192/6622623.jpg",
    "rawText": "ROOF TILE 2X2/45 INV.\n\n6622623\n\nSelect this piece"
  },
  {
    "id": "6670644",
    "name": "FOOT, PLATE",
    "imageUrl": "https://www.lego.com/cdn/product-assets/element.img.lod5photo.192x192/6670644.jpg",
    "rawText": "FOOT, PLATE\n\n6670644\n\nSelect this piece"
  },
  {
    "id": "6385229",
    "name": "LATTICE 3X6 MODULE W/KNOBS",
    "imageUrl": "https://www.lego.com/cdn/product-assets/element.img.lod5photo.192x192/6385229.jpg",
    "rawText": "LATTICE 3X6 MODULE W/KNOBS\n\n6385229\n\nSelect this piece"
  },
  {
    "id": "6013866",
    "name": "FLAT TILE 2X2 INV.",
    "imageUrl": "https://www.lego.com/cdn/product-assets/element.img.lod5photo.192x192/6013866.jpg",
    "rawText": "FLAT TILE 2X2 INV.\n\n6013866\n\nSelect this piece"
  },
  {
    "id": "6064097",
    "name": "SKATEBOARD",
    "imageUrl": "https://www.lego.com/cdn/product-assets/element.img.lod5photo.192x192/6064097.jpg",
    "rawText": "SKATEBOARD\n\n6064097\n\nSelect this piece"
  },
  {
    "id": "6335115",
    "name": "WHEEL BEARING 2X4X1 1/3 W/ CROSS HOLE",
    "imageUrl": "https://www.lego.com/cdn/product-assets/element.img.lod5photo.192x192/6335115.jpg",
    "rawText": "WHEEL BEARING 2X4X1 1/3 W/ CROSS HOLE\n\n6335115\n\nSelect this piece"
  },
  {
    "id": "6097511",
    "name": "PLATE 2X4",
    "imageUrl": "https://www.lego.com/cdn/product-assets/element.img.lod5photo.192x192/6097511.jpg",
    "rawText": "PLATE 2X4\n\n6097511\n\nSelect this piece"
  },
  {
    "id": "6138657",
    "name": "SKATER HELMET",
    "imageUrl": "https://www.lego.com/cdn/product-assets/element.img.lod5photo.192x192/6138657.jpg",
    "rawText": "SKATER HELMET\n\n6138657\n\nSelect this piece"
  },
  {
    "id": "6242241",
    "name": "PLATE 1X1, W/ 1.5 PLATE 1X1, UPWARDS",
    "imageUrl": "https://www.lego.com/cdn/product-assets/element.img.lod5photo.192x192/6242241.jpg",
    "rawText": "PLATE 1X1, W/ 1.5 PLATE 1X1, UPWARDS\n\n6242241\n\nSelect this piece"
  },
  {
    "id": "4261565",
    "name": "PLATE 4X6X2/3",
    "imageUrl": "https://www.lego.com/cdn/product-assets/element.img.lod5photo.192x192/4261565.jpg",
    "rawText": "PLATE 4X6X2/3\n\n4261565\n\nSelect this piece"
  },
  {
    "id": "614123",
    "name": "ROUND PLATE 1X1",
    "imageUrl": "https://www.lego.com/cdn/cs/set/assets/bltfbda7f610964cba5/614123.jpg",
    "rawText": "ROUND PLATE 1X1\n\n614123\n\nSelect this piece"
  },
  {
    "id": "6348055",
    "name": "PLATE 1X1 W. UP RIGHT HOLDER",
    "imageUrl": "https://www.lego.com/cdn/cs/set/assets/blta836109309e96482/6348055.jpg",
    "rawText": "PLATE 1X1 W. UP RIGHT HOLDER\n\n6348055\n\nSelect this piece"
  },
  {
    "id": "4211413",
    "name": "FLAT TILE 2X2",
    "imageUrl": "https://www.lego.com/cdn/product-assets/element.img.lod5photo.192x192/4211413.jpg",
    "rawText": "FLAT TILE 2X2\n\n4211413\n\nSelect this piece"
  },
  {
    "id": "6514189",
    "name": "FLAT TILE 1X1, ROUND",
    "imageUrl": "https://www.lego.com/cdn/product-assets/element.img.lod5photo.192x192/6514189.jpg",
    "rawText": "FLAT TILE 1X1, ROUND\n\n6514189\n\nSelect this piece"
  },
  {
    "id": "6133805",
    "name": "FOOT, PLATE",
    "imageUrl": "https://www.lego.com/cdn/product-assets/element.img.lod5photo.192x192/6133805.jpg",
    "rawText": "FOOT, PLATE\n\n6133805\n\nSelect this piece"
  },
  {
    "id": "6540972",
    "name": "PLATE 1X1, W/ 1.5 PLATE 1X2, DOWNWARDS",
    "imageUrl": "https://www.lego.com/cdn/product-assets/element.img.lod5photo.192x192/6540972.jpg",
    "rawText": "PLATE 1X1, W/ 1.5 PLATE 1X2, DOWNWARDS\n\n6540972\n\nSelect this piece"
  },
  {
    "id": "6424021",
    "name": "PADDLE, NO. 1",
    "imageUrl": "https://www.lego.com/cdn/product-assets/element.img.lod5photo.192x192/6424021.jpg",
    "rawText": "PADDLE, NO. 1\n\n6424021\n\nSelect this piece"
  },
  {
    "id": "6509803",
    "name": "SPORT EQUIPMENT, NO. 3",
    "imageUrl": "https://www.lego.com/cdn/product-assets/element.img.lod5photo.192x192/6509803.jpg",
    "rawText": "SPORT EQUIPMENT, NO. 3\n\n6509803\n\nSelect this piece"
  },
  {
    "id": "6092956",
    "name": "STEE.WHEEL Ø16 F/CONSOLE 2X2",
    "imageUrl": "https://www.lego.com/cdn/product-assets/element.img.lod5photo.192x192/6092956.jpg",
    "rawText": "STEE.WHEEL Ø16 F/CONSOLE 2X2\n\n6092956\n\nSelect this piece"
  },
  {
    "id": "6287856",
    "name": "FLAT TILE 1X1, ROUND NO. 56",
    "imageUrl": "https://www.lego.com/cdn/product-assets/element.img.lod5photo.192x192/6287856.jpg",
    "rawText": "FLAT TILE 1X1, ROUND NO. 56\n\n6287856\n\nSelect this piece"
  },
  {
    "id": "6329593",
    "name": "FLAT TILE 1X1, ROUND, NO. 148",
    "imageUrl": "https://www.lego.com/cdn/product-assets/element.img.lod5photo.192x192/6329593.jpg",
    "rawText": "FLAT TILE 1X1, ROUND, NO. 148\n\n6329593\n\nSelect this piece"
  },
  {
    "id": "6542056",
    "name": "FLAT TILE 1X2, NO. 477",
    "imageUrl": "https://www.lego.com/cdn/product-assets/element.img.lod5photo.192x192/6542056.jpg",
    "rawText": "FLAT TILE 1X2, NO. 477\n\n6542056\n\nSelect this piece"
  },
  {
    "id": "6099243",
    "name": "ANGULAR PLATE 1.5 BOT. 1X2 1/2",
    "imageUrl": "https://www.lego.com/cdn/cs/set/assets/blt35d4cc317e5f5fea/6099243.jpg",
    "rawText": "ANGULAR PLATE 1.5 BOT. 1X2 1/2\n\n6099243\n\nSelect this piece"
  },
  {
    "id": "6528544",
    "name": "WALL 2X2X1 W/ KNOB",
    "imageUrl": "https://www.lego.com/cdn/product-assets/element.img.lod5photo.192x192/6528544.jpg",
    "rawText": "WALL 2X2X1 W/ KNOB\n\n6528544\n\nSelect this piece"
  },
  {
    "id": "6093479",
    "name": "FOOT, PLATE",
    "imageUrl": "https://www.lego.com/cdn/cs/set/assets/blt570535f44f0de57f/6093479.jpg",
    "rawText": "FOOT, PLATE\n\n6093479\n\nSelect this piece"
  },
  {
    "id": "6168618",
    "name": "ANGLE PLATE 1X2/1X4",
    "imageUrl": "https://www.lego.com/cdn/product-assets/element.img.lod5photo.192x192/6168618.jpg",
    "rawText": "ANGLE PLATE 1X2/1X4\n\n6168618\n\nSelect this piece"
  },
  {
    "id": "6421682",
    "name": "WHEEL AXLE Ø8.2/Ø1.9",
    "imageUrl": "https://www.lego.com/cdn/product-assets/element.img.lod5photo.192x192/6421682.jpg",
    "rawText": "WHEEL AXLE Ø8.2/Ø1.9\n\n6421682\n\nSelect this piece"
  },
  {
    "id": "6096991",
    "name": "SUNGLASSES W. 1,5 CONNECTOR",
    "imageUrl": "https://www.lego.com/cdn/product-assets/element.img.lod5photo.192x192/6096991.jpg",
    "rawText": "SUNGLASSES W. 1,5 CONNECTOR\n\n6096991\n\nSelect this piece"
  },
  {
    "id": "6056226",
    "name": "CHEST 2X4",
    "imageUrl": "https://www.lego.com/cdn/product-assets/element.img.lod5photo.192x192/6056226.jpg",
    "rawText": "CHEST 2X4\n\n6056226\n\nSelect this piece"
  },
  {
    "id": "6540970",
    "name": "KAYAK 2X15",
    "imageUrl": "https://www.lego.com/cdn/product-assets/element.img.lod5photo.192x192/6540970.jpg",
    "rawText": "KAYAK 2X15\n\n6540970\n\nSelect this piece"
  },
  {
    "id": "6097509",
    "name": "PLATE 2X6",
    "imageUrl": "https://www.lego.com/cdn/product-assets/element.img.lod5photo.192x192/6097509.jpg",
    "rawText": "PLATE 2X6\n\n6097509\n\nSelect this piece"
  },
  {
    "id": "6065504",
    "name": "FLAT TILE 1X1",
    "imageUrl": "https://www.lego.com/cdn/cs/set/assets/blta625a8493aff3e63/6065504.jpg",
    "rawText": "FLAT TILE 1X1\n\n6065504\n\nSelect this piece"
  },
  {
    "id": "306924",
    "name": "FLAT TILE 1X2",
    "imageUrl": "https://www.lego.com/cdn/cs/set/assets/blt4b7c0b4243891d06/306924.jpg",
    "rawText": "FLAT TILE 1X2\n\n306924\n\nSelect this piece"
  },
  {
    "id": "6503221",
    "name": "WINDSCREEN 6X3X2",
    "imageUrl": "https://www.lego.com/cdn/product-assets/element.img.lod5photo.192x192/6503221.jpg",
    "rawText": "WINDSCREEN 6X3X2\n\n6503221\n\nSelect this piece"
  },
  {
    "id": "6020074",
    "name": "PLATE 1X6",
    "imageUrl": "https://www.lego.com/cdn/product-assets/element.img.lod5photo.192x192/6020074.jpg",
    "rawText": "PLATE 1X6\n\n6020074\n\nSelect this piece"
  },
  {
    "id": "4210997",
    "name": "PLATE 2X8",
    "imageUrl": "https://www.lego.com/cdn/cs/set/assets/blt97a7c652adde3f2c/4210997.jpg",
    "rawText": "PLATE 2X8\n\n4210997\n\nSelect this piece"
  },
  {
    "id": "4640844",
    "name": "Ø3.2 SHAFT W. CORED KNOB",
    "imageUrl": "https://www.lego.com/cdn/cs/set/assets/bltf3f442c406b80780/4640844.jpg",
    "rawText": "Ø3.2 SHAFT W. CORED KNOB\n\n4640844\n\nSelect this piece"
  },
  {
    "id": "6073040",
    "name": "PLATE 1X1",
    "imageUrl": "https://www.lego.com/cdn/product-assets/element.img.lod5photo.192x192/6073040.jpg",
    "rawText": "PLATE 1X1\n\n6073040\n\nSelect this piece"
  },
  {
    "id": "4211000",
    "name": "ROOF TILE 2X2/45° INV.",
    "imageUrl": "https://www.lego.com/cdn/cs/set/assets/blt667a89623d61e7a8/4211000.jpg",
    "rawText": "ROOF TILE 2X2/45° INV.\n\n4211000\n\nSelect this piece"
  },
  {
    "id": "302321",
    "name": "PLATE 1X2",
    "imageUrl": "https://www.lego.com/cdn/cs/set/assets/blt442393b96359694d/302321.jpg",
    "rawText": "PLATE 1X2\n\n302321\n\nSelect this piece"
  },
  {
    "id": "306901",
    "name": "FLAT TILE 1X2",
    "imageUrl": "https://www.lego.com/cdn/product-assets/element.img.lod5photo.192x192/306901.jpg",
    "rawText": "FLAT TILE 1X2\n\n306901\n\nSelect this piece"
  },
  {
    "id": "4211438",
    "name": "PLATE 1X6",
    "imageUrl": "https://www.lego.com/cdn/cs/set/assets/blt3347654f569e6f29/4211438.jpg",
    "rawText": "PLATE 1X6\n\n4211438\n\nSelect this piece"
  }
]