[
  {
    "id": "6465247",
    "name": "PLATE 1X1",
    "imageUrl": "https://www.lego.com/cdn/product-assets/element.img.lod5photo.192x192/6465247.jpg",
    "rawText": "PLATE 1X1\n\n6465247\n\nSelect this piece"
  },
  {
    "id": "6388133",
    "name": "PLATE 1X1X2/3",
    "imageUrl": "https://www.lego.com/cdn/product-assets/element.img.lod5photo.192x192/6388133.jpg",
    "rawText": "PLATE 1X1X2/3\n\n6388133\n\nSelect this piece"
  },
  {
    "id": "300223",
    "name": "BRICK 2X3",
    "imageUrl": "https://www.lego.com/cdn/cs/set/assets/bltf2eaeb3c59fc3c2b/300223.jpg",
    "rawText": "BRICK 2X3\n\n300223\n\nSelect this piece"
  },
  {
    "id": "243121",
    "name": "FLAT TILE 1X4",
    "imageUrl": "https://www.lego.com/cdn/cs/set/assets/blt2097c438230606f4/243121.jpg",
    "rawText": "FLAT TILE 1X4\n\n243121\n\nSelect this piece"
  },
  {
    "id": "6408542",
    "name": "WHEEL SUSPENSION 2X4 W/ SNAP",
    "imageUrl": "https://www.lego.com/cdn/product-assets/element.img.lod5photo.192x192/6408542.jpg",
    "rawText": "WHEEL SUSPENSION 2X4 W/ SNAP\n\n6408542\n\nSelect this piece"
  },
  {
    "id": "6070695",
    "name": "FLAT TILE 2X2, ROUND",
    "imageUrl": "https://www.lego.com/cdn/cs/set/assets/blt85f95dd7bd3db9f2/6070695.jpg",
    "rawText": "FLAT TILE 2X2, ROUND\n\n6070695\n\nSelect this piece"
  },
  {
    "id": "4211397",
    "name": "PLATE 2X2",
    "imageUrl": "https://www.lego.com/cdn/product-assets/element.img.lod5photo.192x192/4211397.jpg",
    "rawText": "PLATE 2X2\n\n4211397\n\nSelect this piece"
  },
  {
    "id": "6606824",
    "name": "BI 3108, 60+4, 60482 V29",
    "imageUrl": "https://www.lego.com/cdn/product-assets/element.img.lod5photo.192x192/6606824.jpg",
    "rawText": "BI 3108, 60+4, 60482 V29\n\n6606824\n\nSelect this piece"
  },
  {
    "id": "73081",
    "name": "CONSOLE W/ST.WHEEL BL/BL",
    "imageUrl": "https://www.lego.com/cdn/product-assets/element.img.lod5photo.192x192/73081.jpg",
    "rawText": "CONSOLE W/ST.WHEEL BL/BL\n\n73081\n\nSelect this piece"
  },
  {
    "id": "6514185",
    "name": "WALL ELEMENT 1X2X2",
    "imageUrl": "https://www.lego.com/cdn/cs/set/assets/https://www.lego.com/cdn/cs/elements/assets/blt07a8843a78cdb8ec/6514185.jpg",
    "rawText": "WALL ELEMENT 1X2X2\n\n6514185\n\nSelect this piece"
  },
  {
    "id": "366601",
    "name": "PLATE 1X6",
    "imageUrl": "https://www.lego.com/cdn/cs/set/assets/blta25ebd5b1abff696/366601.jpg",
    "rawText": "PLATE 1X6\n\n366601\n\nSelect this piece"
  },
  {
    "id": "243221",
    "name": "CLAMP 1X2",
    "imageUrl": "https://www.lego.com/cdn/cs/set/assets/bltf5196f49316cb012/243221.jpg",
    "rawText": "CLAMP 1X2\n\n243221\n\nSelect this piece"
  },
  {
    "id": "6583786",
    "name": "MINI FIGURE, BABY HEAD, NO. 18",
    "imageUrl": "https://www.lego.com/cdn/product-assets/element.img.lod5photo.192x192/6583786.jpg",
    "rawText": "MINI FIGURE, BABY HEAD, NO. 18\n\n6583786\n\nSelect this piece"
  },
  {
    "id": "6588088",
    "name": "BRICK 1X2X2, NO. 286",
    "imageUrl": "https://www.lego.com/cdn/product-assets/element.img.lod5photo.192x192/6588088.jpg",
    "rawText": "BRICK 1X2X2, NO. 286\n\n6588088\n\nSelect this piece"
  },
  {
    "id": "6585272",
    "name": "MINI FIGUR BABY BODY",
    "imageUrl": "https://www.lego.com/cdn/product-assets/element.img.lod5photo.192x192/6585272.jpg",
    "rawText": "MINI FIGUR BABY BODY\n\n6585272\n\nSelect this piece"
  },
  {
    "id": "6382324",
    "name": "PLATE 1X2",
    "imageUrl": "https://www.lego.com/cdn/product-assets/element.img.lod5photo.192x192/6382324.jpg",
    "rawText": "PLATE 1X2\n\n6382324\n\nSelect this piece"
  },
  {
    "id": "6118832",
    "name": "ANGLE PLATE 1X2 / 2X4",
    "imageUrl": "https://www.lego.com/cdn/cs/set/assets/bltc962d35e3e83eba7/6118832.jpg",
    "rawText": "ANGLE PLATE 1X2 / 2X4\n\n6118832\n\nSelect this piece"
  },
  {
    "id": "4521681",
    "name": "LATTICE PLATE 1X4X3",
    "imageUrl": "https://www.lego.com/cdn/cs/set/assets/blt29cbefb2a3c11c63/4521681.jpg",
    "rawText": "LATTICE PLATE 1X4X3\n\n4521681\n\nSelect this piece"
  },
  {
    "id": "4600178",
    "name": "MUDGUARD 2X4 w. hole Ø4.9",
    "imageUrl": "https://www.lego.com/cdn/cs/set/assets/bltbcc0a5e4e215250d/4600178.jpg",
    "rawText": "MUDGUARD 2X4 w. hole Ø4.9\n\n4600178\n\nSelect this piece"
  },
  {
    "id": "302021",
    "name": "PLATE 2X4",
    "imageUrl": "https://www.lego.com/cdn/cs/set/assets/blte2b3747cd61d84c2/302021.jpg",
    "rawText": "PLATE 2X4\n\n302021\n\nSelect this piece"
  },
  {
    "id": "301021",
    "name": "BRICK 1X4",
    "imageUrl": "https://www.lego.com/cdn/cs/set/assets/blta351a3b1c22f988e/301021.jpg",
    "rawText": "BRICK 1X4\n\n301021\n\nSelect this piece"
  },
  {
    "id": "6510179",
    "name": "FLAT TILE 1X4",
    "imageUrl": "https://www.lego.com/cdn/product-assets/element.img.lod5photo.192x192/6510179.jpg",
    "rawText": "FLAT TILE 1X4\n\n6510179\n\nSelect this piece"
  },
  {
    "id": "6514191",
    "name": "FLAT TILE 1X1, ROUND",
    "imageUrl": "https://www.lego.com/cdn/product-assets/element.img.lod5photo.192x192/6514191.jpg",
    "rawText": "FLAT TILE 1X1, ROUND\n\n6514191\n\nSelect this piece"
  },
  {
    "id": "241226",
    "name": "RADIATOR GRILLE 1X2",
    "imageUrl": "https://www.lego.com/cdn/cs/set/assets/blt5d25bf36e28392b2/241226.jpg",
    "rawText": "RADIATOR GRILLE 1X2\n\n241226\n\nSelect this piece"
  },
  {
    "id": "407021",
    "name": "ANGULAR BRICK 1X1",
    "imageUrl": "https://www.lego.com/cdn/product-assets/element.img.lod5photo.192x192/407021.jpg",
    "rawText": "ANGULAR BRICK 1X1\n\n407021\n\nSelect this piece"
  },
  {
    "id": "6579692",
    "name": "PLATE 4X4, W/ 4 KNOBS, NO. 41",
    "imageUrl": "https://www.lego.com/cdn/product-assets/element.img.lod5photo.192x192/6579692.jpg",
    "rawText": "PLATE 4X4, W/ 4 KNOBS, NO. 41\n\n6579692\n\nSelect this piece"
  },
  {
    "id": "6146217",
    "name": "WALL ELEMENT 1X2X1",
    "imageUrl": "https://www.lego.com/cdn/product-assets/element.img.lod5photo.192x192/6146217.jpg",
    "rawText": "WALL ELEMENT 1X2X1\n\n6146217\n\nSelect this piece"
  },
  {
    "id": "6663108",
    "name": "PLATE 2X2 W 1 KNOB",
    "imageUrl": "https://www.lego.com/cdn/product-assets/element.img.lod5photo.192x192/6663108.jpg",
    "rawText": "PLATE 2X2 W 1 KNOB\n\n6663108\n\nSelect this piece"
  },
  {
    "id": "4613153",
    "name": "PLATE W. BOW 1X4X2/3",
    "imageUrl": "https://www.lego.com/cdn/cs/set/assets/blt1e614eac65fff277/4613153.jpg",
    "rawText": "PLATE W. BOW 1X4X2/3\n\n4613153\n\nSelect this piece"
  },
  {
    "id": "6336858",
    "name": "WHEEL, DIA. 24X12",
    "imageUrl": "https://www.lego.com/cdn/product-assets/element.img.lod5photo.192x192/6336858.jpg",
    "rawText": "WHEEL, DIA. 24X12\n\n6336858\n\nSelect this piece"
  },
  {
    "id": "6514189",
    "name": "FLAT TILE 1X1, ROUND",
    "imageUrl": "https://www.lego.com/cdn/product-assets/element.img.lod5photo.192x192/6514189.jpg",
    "rawText": "FLAT TILE 1X1, ROUND\n\n6514189\n\nSelect this piece"
  },
  {
    "id": "6586851",
    "name": "PLATE 1X1X2/3, OUTSIDE BOW",
    "imageUrl": "https://www.lego.com/cdn/product-assets/element.img.lod5photo.192x192/6586851.jpg",
    "rawText": "PLATE 1X1X2/3, OUTSIDE BOW\n\n6586851\n\nSelect this piece"
  },
  {
    "id": "6507908",
    "name": "WINDSCREEN 2X4X2",
    "imageUrl": "https://www.lego.com/cdn/product-assets/element.img.lod5photo.192x192/6507908.jpg",
    "rawText": "WINDSCREEN 2X4X2\n\n6507908\n\nSelect this piece"
  },
  {
    "id": "4565323",
    "name": "PLATE 2X2 W 1 KNOB",
    "imageUrl": "https://www.lego.com/cdn/product-assets/element.img.lod5photo.192x192/4565323.jpg",
    "rawText": "PLATE 2X2 W 1 KNOB\n\n4565323\n\nSelect this piece"
  },
  {
    "id": "6443446",
    "name": "MUDGUARD 2X4X2, NO. 2",
    "imageUrl": "https://www.lego.com/cdn/product-assets/element.img.lod5photo.192x192/6443446.jpg",
    "rawText": "MUDGUARD 2X4X2, NO. 2\n\n6443446\n\nSelect this piece"
  },
  {
    "id": "4210997",
    "name": "PLATE 2X8",
    "imageUrl": "https://www.lego.com/cdn/cs/set/assets/blt97a7c652adde3f2c/4210997.jpg",
    "rawText": "PLATE 2X8\n\n4210997\n\nSelect this piece"
  },
  {
    "id": "302221",
    "name": "PLATE 2X2",
    "imageUrl": "https://www.lego.com/cdn/cs/set/assets/blt58f70c53093df0b0/302221.jpg",
    "rawText": "PLATE 2X2\n\n302221\n\nSelect this piece"
  },
  {
    "id": "6347310",
    "name": "PLATE 1X2 W. VERTICAL GRIP",
    "imageUrl": "https://www.lego.com/cdn/product-assets/element.img.lod5photo.192x192/6347310.jpg",
    "rawText": "PLATE 1X2 W. VERTICAL GRIP\n\n6347310\n\nSelect this piece"
  }
]